<?xml version="1.0" encoding="UTF-8"?>
<Commands>
    <CmdGroup Title="Device Settings" Icon="&#xe91e;" CanRead="false">
        <WriteCmd Title="Reset" Cmd="reset" CheckedIcon="&#xe8fd;" UnCheckedIcon="&#xe8fd;">
			<CmdResOK>ok</CmdResOK>
		</WriteCmd>
		<ReadAllCmd Title="Read Config" Cmd="" Icon="&#xe8d0;">
		</ReadAllCmd>
		<WrtReadCmd Title="CEC Broadcast" Cmd1="cec on" Cmd2="cec off" CmdRes="ok" ReadCmd = "cec" Sequence = "5">
			<ReadRes Title="CEC On">cec on</ReadRes>
			<ReadRes Title="CEC Off">cec off</ReadRes>
		</WrtReadCmd>
		<WrtReadCmd Title="Power" Cmd1="pwr on" Cmd2="pwr off" CmdRes="ok" ReadCmd = "power" Sequence = "6">
			<ReadRes Title="Power On">power on</ReadRes>
			<ReadRes Title="Power Off">power off</ReadRes>
		</WrtReadCmd>
		<WrtReadCmd Title="Auto Switch" Cmd1="autosw on" Cmd2="autosw off" CmdRes="ok" ReadCmd = "autosw" Sequence = "7">
			<ReadRes Title="Auto Switch On">autosw on</ReadRes>
			<ReadRes Title="Auto Switch Off">autosw off</ReadRes>
		</WrtReadCmd>
		<ReadCmd Title="Info" Cmd="man">
			<CmdRes Title="" refWmdID = "-1">man Integral</CmdRes>
		</ReadCmd>
    </CmdGroup>
	<CmdGroup Title="Channel Selection" Icon="&#xeaa0;" CanRead="true" Sequence="0" Try="2">
        <WriteCmdChk Title="Channel/Input 1" Cmd="insel 1">
			<CmdResOK>ok</CmdResOK>
		</WriteCmdChk>
		<WriteCmdChk Title="Channel/Input 2" Cmd="insel 2">
			<CmdResOK>ok</CmdResOK>
		</WriteCmdChk>
		<WriteCmdChk Title="Matrix Thru" Cmd="insel 3">
			<CmdResOK>ok</CmdResOK>
		</WriteCmdChk>		
		<WriteCmdChk Title="Matrix Swap" Cmd="insel 4">
			<CmdResOK>ok</CmdResOK>
		</WriteCmdChk>		
		<ReadCmd Title="Read Channel" Cmd="insel">
			<CmdRes Title="Input 1" refWmdID = "0">insel 1</CmdRes>
			<CmdRes Title="Input 2" refWmdID = "1">insel 2</CmdRes>
            <CmdRes Title="Matrix Thru" refWmdID = "2">insel 3</CmdRes>
           	<CmdRes Title="Matrix Swap" refWmdID = "3">insel 4</CmdRes>
		</ReadCmd>
    </CmdGroup>
	<CmdGroup Title="HDCP Settings" Icon="&#xeaff;" CanRead="true" Sequence="1" Try="2">
	    <WriteCmdChk Title="HDCP 1.4 only" Cmd="hdcp 14">
			<CmdResOK>ok</CmdResOK>
			<CmdResSWForce>swforce</CmdResSWForce>
		</WriteCmdChk>
        <WriteCmdChk Title="HDCP 2.2 + 1.4" Cmd="hdcp 22">
			<CmdResOK>ok</CmdResOK>
			<CmdResSWForce>swforce</CmdResSWForce>
		</WriteCmdChk>
		<ReadCmd Title="Read HDCP" Cmd="hdcp" Icon="&#xeaa0;">
			<CmdRes Title="1.4 only" refWmdID = "0">hdcp 14</CmdRes>
			<CmdRes Title="2.2 + 1.4" refWmdID = "1">hdcp 22</CmdRes>
			<CmdRes Title="Auto" refWmdID = "-1">hdcp auto</CmdRes>
		</ReadCmd>
    </CmdGroup>	
    <CmdGroup Title="Sound Settings" Icon="&#xeb47;" CanRead="true" Sequence="2" Try="2">
        <WriteCmdChk Title="External Audio" Cmd="audio jack">
			<CmdResOK>ok</CmdResOK>
			<CmdResSWForce>swforce</CmdResSWForce>
		</WriteCmdChk>
        <WriteCmdChk Title="From HDMI" Cmd="audio hdmi">
			<CmdResOK>ok</CmdResOK>
			<CmdResSWForce>swforce</CmdResSWForce>
		</WriteCmdChk>
		<WrtReadCmd Title="Mute All Sound" Cmd1="mute on" Cmd2="mute off" CmdRes="ok" ReadCmd = "mute" Sequence = "8">
			<ReadRes Title="Mute On">mute on</ReadRes>
			<ReadRes Title="Mute Off">mute off</ReadRes>
		</WrtReadCmd>
		<ReadCmd Title="Read Audio" Cmd="audio" Icon="&#xeaa0;">
			<CmdRes Title="HDMI" refWmdID = "1">audio hdmi</CmdRes>
			<CmdRes Title="External" refWmdID = "0">audio jack</CmdRes>
			<CmdRes Title="Auto" refWmdID = "-1">audio auto</CmdRes>
		</ReadCmd>
    </CmdGroup>
	<CmdGroup Title="EDID Settings" Icon="&#xe8c7;" CanRead="true" Sequence="3" Try="2">
	    <WriteCmdChk Title="Auto Mix Mode" Cmd="edid automix">
			<CmdResOK>ok</CmdResOK>
			<CmdResSWForce>swforce</CmdResSWForce>
		</WriteCmdChk>
		<WriteCmdChk Title="Custom" Cmd="edid custom">
			<CmdResOK>ok</CmdResOK>
			<CmdResSWForce>swforce</CmdResSWForce>
		</WriteCmdChk>
        <WriteCmdChk Title="Fixed With L/R Stereo" Cmd="edid fixed">
			<CmdResOK>ok</CmdResOK>
			<CmdResSWForce>swforce</CmdResSWForce>
		</WriteCmdChk>
		<ReadCmd Title="Read EDID" Cmd="edid">
			<CmdRes Title="L/R stereo" refWmdID = "2">edid fixed</CmdRes>
			<CmdRes Title="Custom" refWmdID = "1">edid custom</CmdRes>
			<CmdRes Title="Mix" refWmdID = "0">edid automix</CmdRes>
		</ReadCmd>
    </CmdGroup>
    <CmdGroup Title="Convert 4K60 4:4:4 > 4:2:0" Icon="&#xea90;" CanRead="true" Sequence="4" Try="1">
	    <WriteCmdChk Title="On" Cmd="420 on">
			<CmdResOK>ok</CmdResOK>
		</WriteCmdChk>
	    <WriteCmdChk Title="Off" Cmd="420 off">
			<CmdResOK>ok</CmdResOK>
		</WriteCmdChk>
		<ReadCmd Title="Read Current 4:2:0 Selection Status" Cmd="420">
			<CmdRes Title="On" refWmdID = "0">420 on</CmdRes>
			<CmdRes Title="Off" refWmdID = "1">420 off</CmdRes>
		</ReadCmd>
    </CmdGroup>
    <CmdGroup Title="Play with CEC" Icon="&#xe860;" CanRead="false">
	    <WriteCmd Title="Turn Everything On" Cmd="CEC 0F:04" CheckedIcon="&#xea9d;" UnCheckedIcon="&#xea9d;">
			<CmdResOK>ok</CmdResOK>
		</WriteCmd>
	    <WriteCmd Title="Turn Everything Off" Cmd="CEC 0F:36" CheckedIcon="&#xea9d;" UnCheckedIcon="&#xea9d;">
			<CmdResOK>ok</CmdResOK>
		</WriteCmd>   
		<WriteCECCmd Title="Define CEC1 SP" PreCmd = "cec1save" Cmd="0F:36" Icon="&#xea67;">
			<CmdRes>ok</CmdRes>
		</WriteCECCmd>
		<WriteCECCmd Title="Define CEC2 LP" PreCmd = "cec2save" Cmd="0F:36" Icon="&#xea67;">
			<CmdRes>ok</CmdRes>
		</WriteCECCmd>
		<WriteCECCmd Title="Play CEC Command" PreCmd = "CEC" Cmd="0F:36" Icon="&#xea9d;">
			<CmdRes>ok</CmdRes>
		</WriteCECCmd>
		<ReadCmd Title="Read CEC status" Cmd="cec">
			<CmdRes Title="On" refWmdID = "0">cec on</CmdRes>
			<CmdRes Title="Off" refWmdID = "1">cec off</CmdRes>
		</ReadCmd>
    </CmdGroup>
    <CmdGroup Title="CEC Playback1" Icon="&#xeaa4;" CanRead="false">
	    <CECChildItem CheckedIcon1="&#xeacb;" UnCheckedIcon1="&#xeacb;" Cmd1 = "CEC 54:44:4C" 
	              CheckedIcon2="&#xea7d;" UnCheckedIcon2="&#xea7d;" Cmd2 = "CEC 54:44:44" 
	              CheckedIcon3="&#xea64;" UnCheckedIcon3="&#xea64;" Cmd3 = "CEC 54:44:46" 
	              CheckedIcon4="&#xeaca;" UnCheckedIcon4="&#xeaca;" Cmd4 = "CEC 54:44:4B"/>
	    <CECChildItem CheckedIcon1="&#xe9be;" UnCheckedIcon1="&#xe9be;" Cmd1 = "CEC 54:44:09" 
	              CheckedIcon2="" UnCheckedIcon2="" Cmd2 = "CEC 0F:36" 
	              CheckedIcon3="&#xe815;" UnCheckedIcon3="&#xe815;" Cmd3 = "CEC 54:44:01" 
	              CheckedIcon4="" UnCheckedIcon4="" Cmd4 = "CEC 0F:36"/>
		<CECChildItem CheckedIcon1="&#xe9d4;" UnCheckedIcon1="&#xe9d4;" Cmd1 = "CEC 54:44:35" 
			CheckedIcon2="&#xe8f9;" UnCheckedIcon2="&#xe8f9;" Cmd2 = "CEC 54:44:03" 
			CheckedIcon3="&#xe810;" UnCheckedIcon3="&#xe810;" Cmd3 = "CEC 54:44:00" 
			CheckedIcon4="&#xe811;" UnCheckedIcon4="&#xe811;" Cmd4 = "CEC 54:44:04"/>	
		<CECChildItem CheckedIcon1="&#xe885;" UnCheckedIcon1="&#xe884;" Cmd1 = "CEC 54:44:0D" 
			CheckedIcon2="" UnCheckedIcon2="" Cmd2 = "CEC 0F:36" 
			CheckedIcon3="&#xe8f4;" UnCheckedIcon3="&#xe8f4;" Cmd3 = "CEC 54:44:02" 
			CheckedIcon4="" UnCheckedIcon4="" Cmd4 = "CEC 0F:36"/>
	</CmdGroup>		  
</Commands>